refactory/__init__.py
refactory/data_model.py
refactory/log_utils.py
refactory/py.typed
refactory/spec.py
refactory-0.0.1.dist-info/LICENSE
refactory-0.0.1.dist-info/METADATA
refactory-0.0.1.dist-info/WHEEL
refactory-0.0.1.dist-info/top_level.txt
refactory-0.0.1.dist-info/RECORD
